rule4ml/__init__.py
rule4ml/_version.py
rule4ml/models/__init__.py
rule4ml/models/architectures.py
rule4ml/models/callbacks.py
rule4ml/models/metrics.py
rule4ml/models/scaling.py
rule4ml/models/tuning.py
rule4ml/models/utils.py
rule4ml/models/wrappers.py
rule4ml/models/weights/.gitignore
rule4ml/models/weights/__init__.py
rule4ml/models/weights/v1/mlp/BRAM.config.json
rule4ml/models/weights/v1/mlp/BRAM.weights.h5
rule4ml/models/weights/v1/mlp/CYCLES.config.json
rule4ml/models/weights/v1/mlp/CYCLES.weights.h5
rule4ml/models/weights/v1/mlp/DSP.config.json
rule4ml/models/weights/v1/mlp/DSP.weights.h5
rule4ml/models/weights/v1/mlp/FF.config.json
rule4ml/models/weights/v1/mlp/FF.weights.h5
rule4ml/models/weights/v1/mlp/LUT.config.json
rule4ml/models/weights/v1/mlp/LUT.weights.h5
rule4ml/models/weights/v2/gnn/BRAM.config.json
rule4ml/models/weights/v2/gnn/BRAM.weights.pt
rule4ml/models/weights/v2/gnn/CYCLES.config.json
rule4ml/models/weights/v2/gnn/CYCLES.weights.pt
rule4ml/models/weights/v2/gnn/DSP.config.json
rule4ml/models/weights/v2/gnn/DSP.weights.pt
rule4ml/models/weights/v2/gnn/FF.config.json
rule4ml/models/weights/v2/gnn/FF.weights.pt
rule4ml/models/weights/v2/gnn/INTERVAL.config.json
rule4ml/models/weights/v2/gnn/INTERVAL.weights.pt
rule4ml/models/weights/v2/gnn/LUT.config.json
rule4ml/models/weights/v2/gnn/LUT.weights.pt
rule4ml/models/weights/v2/mlp/BRAM.config.json
rule4ml/models/weights/v2/mlp/BRAM.weights.h5
rule4ml/models/weights/v2/mlp/CYCLES.config.json
rule4ml/models/weights/v2/mlp/CYCLES.weights.h5
rule4ml/models/weights/v2/mlp/DSP.config.json
rule4ml/models/weights/v2/mlp/DSP.weights.h5
rule4ml/models/weights/v2/mlp/FF.config.json
rule4ml/models/weights/v2/mlp/FF.weights.h5
rule4ml/models/weights/v2/mlp/INTERVAL.config.json
rule4ml/models/weights/v2/mlp/INTERVAL.weights.h5
rule4ml/models/weights/v2/mlp/LUT.config.json
rule4ml/models/weights/v2/mlp/LUT.weights.h5
rule4ml/parsers/__init__.py
rule4ml/parsers/data_parser.py
rule4ml-0.2.0.dist-info/licenses/LICENSE
rule4ml-0.2.0.dist-info/METADATA
rule4ml-0.2.0.dist-info/WHEEL
rule4ml-0.2.0.dist-info/top_level.txt
rule4ml-0.2.0.dist-info/RECORD
