Metadata-Version: 2.4
Name: rule4ml
Version: 0.2.0
Summary: Resource utilization and Latency Estimation for ML on FPGA
Author: IMPETUS Team
Author-email: impetus@usherbrooke.ca
License: GPL-3.0
Classifier: Development Status :: 4 - Beta
Classifier: Intended Audience :: Developers
Classifier: Intended Audience :: Science/Research
Classifier: License :: OSI Approved :: GNU General Public License v3 (GPLv3)
Classifier: Programming Language :: Python :: 3
Classifier: Programming Language :: Python :: 3 :: Only
Classifier: Topic :: Software Development :: Libraries
Classifier: Topic :: Software Development :: Libraries :: Python Modules
Requires-Python: >=3.9
License-File: LICENSE
Requires-Dist: pandas
Requires-Dist: scikit-learn
Requires-Dist: tensorflow>=2.15.1
Requires-Dist: keras
Requires-Dist: keras_tuner
Requires-Dist: torch
Requires-Dist: torch-geometric
Requires-Dist: optuna
Requires-Dist: tqdm
Provides-Extra: dev
Requires-Dist: pre-commit; extra == "dev"
Requires-Dist: pytest; extra == "dev"
Provides-Extra: datagen
Requires-Dist: hls4ml; extra == "datagen"
Requires-Dist: psutil; extra == "datagen"
Requires-Dist: py-cpuinfo; extra == "datagen"
Requires-Dist: pyparsing; extra == "datagen"
Requires-Dist: tensorflow==2.15.1; extra == "datagen"
Requires-Dist: tf-keras==2.15.1; extra == "datagen"
Dynamic: license-file
